multienum.py
multienum-0.2.3.dist-info/DESCRIPTION.rst
multienum-0.2.3.dist-info/METADATA
multienum-0.2.3.dist-info/metadata.json
multienum-0.2.3.dist-info/pbr.json
multienum-0.2.3.dist-info/RECORD
multienum-0.2.3.dist-info/top_level.txt
multienum-0.2.3.dist-info/WHEEL
