Metadata-Version: 2.0
Name: multienum
Version: 0.2.3
Summary: Enumerator type supporting multiple equivalent names
Home-page: https://github.com/sorreltree/multienum
Author: Michael T Bacon
Author-email: michael@sorreltree.com
License: Apache License 2.0
Keywords: enumeration enum
Platform: UNKNOWN
Classifier: Development Status :: 4 - Beta
Classifier: Intended Audience :: Developers
Classifier: Topic :: Software Development
Classifier: License :: OSI Approved :: Apache Software License
Classifier: Programming Language :: Python :: 2.7
Classifier: Programming Language :: Python :: 3
Classifier: Programming Language :: Python :: 3.2
Classifier: Programming Language :: Python :: 3.3
Classifier: Programming Language :: Python :: 3.4
Provides-Extra: test
Requires-Dist: nose; extra == 'test'
